mylib/__init__.py
mylib/core.py
mylib1_000_000_000-0.2.0.dist-info/licenses/LICENSE
mylib1_000_000_000-0.2.0.dist-info/METADATA
mylib1_000_000_000-0.2.0.dist-info/WHEEL
mylib1_000_000_000-0.2.0.dist-info/top_level.txt
mylib1_000_000_000-0.2.0.dist-info/RECORD
