Metadata-Version: 2.4
Name: mylib1_000_000_000
Version: 0.2.0
Summary: My simple Python library
Author-email: name_0 <example_0@example.com>
Requires-Python: >=3.7
License-File: LICENSE
Dynamic: license-file
